CHANGELOG.rst
LICENSE
MANIFEST.in
README.rst
setup.py
data/create_data_sensitive.py
data/sample_collaborators1.jsonl
data/sample_collaborators2.jsonl
data/sample_triplets.jsonl
docs/.nojekyll
docs/Makefile
docs/index.html
docs/make.bat
quesadiya/__init__.py
quesadiya/cli.py
quesadiya/errors.py
quesadiya/init_admin.py
quesadiya/utils.py
quesadiya.egg-info/PKG-INFO
quesadiya.egg-info/SOURCES.txt
quesadiya.egg-info/dependency_links.txt
quesadiya.egg-info/entry_points.txt
quesadiya.egg-info/not-zip-safe
quesadiya.egg-info/requires.txt
quesadiya.egg-info/top_level.txt
quesadiya/commands/__init__.py
quesadiya/commands/create.py
quesadiya/commands/delete.py
quesadiya/commands/export.py
quesadiya/commands/inspect.py
quesadiya/commands/modify.py
quesadiya/commands/run.py
quesadiya/db/__init__.py
quesadiya/db/config.py
quesadiya/db/factory.py
quesadiya/db/hasher.py
quesadiya/db/interface.py
quesadiya/db/schema.py
quesadiya/db/session.py
quesadiya/django_tool/Pipfile
quesadiya/django_tool/Pipfile.lock
quesadiya/django_tool/__init__.py
quesadiya/django_tool/db.sqlite3
quesadiya/django_tool/info.txt
quesadiya/django_tool/manage.py
quesadiya/django_tool/t
quesadiya/django_tool/Sample data/info.json
quesadiya/django_tool/Sample data/input.json
quesadiya/django_tool/__pycache__/__init__.cpython-37.pyc
quesadiya/django_tool/__pycache__/manage.cpython-37.pyc
quesadiya/django_tool/apps/__init__.py
quesadiya/django_tool/apps/asgi.py
quesadiya/django_tool/apps/settings.py
quesadiya/django_tool/apps/urls.py
quesadiya/django_tool/apps/views.py
quesadiya/django_tool/apps/wsgi.py
quesadiya/django_tool/apps/__pycache__/__init__.cpython-37.pyc
quesadiya/django_tool/apps/__pycache__/asgi.cpython-37.pyc
quesadiya/django_tool/apps/__pycache__/settings.cpython-37.pyc
quesadiya/django_tool/apps/__pycache__/urls.cpython-37.pyc
quesadiya/django_tool/apps/__pycache__/views.cpython-37.pyc
quesadiya/django_tool/apps/__pycache__/wsgi.cpython-37.pyc
quesadiya/django_tool/database/__init__.py
quesadiya/django_tool/database/django_database.py
quesadiya/django_tool/database/insert_utils.py
quesadiya/django_tool/database/__pycache__/__init__.cpython-37.pyc
quesadiya/django_tool/database/__pycache__/django_database.cpython-37.pyc
