Metadata-Version: 1.2
Name: quesadiya
Version: 0.3
Summary: data annotation platform for siamese models
Home-page: https://github.com/SiameseLab/quesadiya
Author: SiameseLab
Author-email: underkey256@gmail.com
License: Apache License 2.0
Keywords: natural language processing,siamese deep neural network,data annotation
Platform: UNKNOWN
Classifier: Programming Language :: Python :: 3 :: Only
Classifier: License :: OSI Approved :: Apache Software License
Classifier: Operating System :: OS Independent
Classifier: Topic :: Scientific/Engineering :: Artificial Intelligence
Requires-Python: >=3.6
